prism/__init__.py
prism/view/__init__.py
prism/view/context.py
prism/view/correlation.py
prism/view/display.py
prism/view/formatter.py
prism/view/handler.py
prism/view/logger.py
prism/view/palette.py
prism/view/scrubber.py
prism/view/setup.py
prism/view/errors/__init__.py
prism/view/errors/base.py
prism/view/errors/categories.py
prism/view/errors/registry.py
prism/view/errors/severity.py
prism/view/errors/standard_codes.py
prism_view-1.0.0.dist-info/METADATA
prism_view-1.0.0.dist-info/WHEEL
prism_view-1.0.0.dist-info/licenses/LICENSE
prism_view-1.0.0.dist-info/RECORD
